{
  "posts": [
    {
      "id": 4,
      "fname": "A. S. M.",
      "lname": "Radwan",
      "eid": "ad21@dasd.bjh",
      "mno": 121231231231,
      "sal": 12312,
      "userid": "323"
    },
    {
      "id": 6,
      "fname": "radwan romy",
      "lname": "romy",
      "eid": "romy@gmail.com",
      "mno": 12312,
      "sal": 1000,
      "userid": "313"
    },
    {
      "id": 13,
      "fname": "radwan",
      "lname": "ds213",
      "eid": "radwan@adf.vhgn",
      "mno": 12,
      "sal": 123,
      "userid": "121"
    }
  ],
  "comments": [],
  "profile": {
    "name": "typicode"
  }
}